atarashi/__init__.py
atarashi/agents/__init__.py
atarashi/agents/atarashiAgent.py
atarashi/agents/cosineSimNgram.py
atarashi/agents/dameruLevenDist.py
atarashi/agents/keywordAgent.py
atarashi/agents/tfidf.py
atarashi/agents/wordFrequencySimilarity.py
atarashi/atarashii.py
atarashi/build_deps.py
atarashi/data/Ngram_keywords.json
atarashi/data/license_keywords.txt
atarashi/data/licenses/2024-12-30T00:00:00Z_3_26_0.csv
atarashi/data/licenses/2025-07-01T00:00:00Z_3_27_0.csv
atarashi/data/licenses/licenseList.csv
atarashi/data/licenses/license_refs_combined.csv
atarashi/data/licenses/processedLicenses.csv
atarashi/evaluator/NomosTestfiles.zip
atarashi/evaluator/TestFiles.zip
atarashi/evaluator/evaluator.py
atarashi/evaluator/keyword_eval.py
atarashi/evaluator/keyword_results.csv
atarashi/imtihaan.py
atarashi/libs/__init__.py
atarashi/libs/commentPreprocessor.py
atarashi/libs/initialmatch.py
atarashi/libs/license_clustering.py
atarashi/libs/ngram.py
atarashi/libs/utils.py
atarashi/license/__init__.py
atarashi/license/licenseDownloader.py
atarashi/license/licenseLoader.py
atarashi/license/licensePreprocessor.py
atarashi/license/license_merger.py
atarashi_rajul-0.0.11.dist-info/LICENSE
atarashi_rajul-0.0.11.dist-info/METADATA
atarashi_rajul-0.0.11.dist-info/WHEEL
atarashi_rajul-0.0.11.dist-info/entry_points.txt
atarashi_rajul-0.0.11.dist-info/RECORD
