Metadata-Version: 2.3
Name: atarashi-rajul
Version: 0.0.11
Summary: An intelligent license scanner.
License: GPL-2.0-only
Keywords: atarashi,license,license-scanner,oss,oss-compliance
Author: Aman Jain
Author-email: amanjain5221@gmail.com
Maintainer: Kaushlendra Pratap Singh
Maintainer-email: kaushlendra-pratap.singh@siemens.com
Requires-Python: >=3.10,<3.14
Classifier: Development Status :: 2 - Pre-Alpha
Classifier: Topic :: Utilities
Classifier: Intended Audience :: Legal Industry
Classifier: License :: OSI Approved :: GNU General Public License v2 (GPLv2)
Requires-Dist: importlib-resources (>=6.5.2,<7.0.0)
Requires-Dist: nirjas (>=1.0.1,<2.0.0)
Requires-Dist: pandas (>=2.3.0,<3.0.0)
Requires-Dist: pyxdameraulevenshtein (>=1.8.0,<2.0.0)
Requires-Dist: scikit-learn (>=1.7.0,<2.0.0)
Requires-Dist: scipy (>=1.15.3,<2.0.0)
Requires-Dist: setuptools (>=80.9.0,<81.0.0)
Requires-Dist: spacy (>=3.8.7,<4.0.0)
Requires-Dist: textdistance (>=4.6.3,<5.0.0)
Requires-Dist: tqdm (>=4.67.1,<5.0.0)
Requires-Dist: twine (>=6.1.0,<7.0.0)
Requires-Dist: urllib3 (>=2.4.0,<3.0.0)
Project-URL: Homepage, https://github.com/fossology/atarashi
Project-URL: Repository, https://github.com/fossology/atarashi
